setup.py
oncodriveclust/__init__.py
oncodriveclust/analysis.py
oncodriveclust/command.py
oncodriveclust/utils.py
oncodriveclust.egg-info/PKG-INFO
oncodriveclust.egg-info/SOURCES.txt
oncodriveclust.egg-info/dependency_links.txt
oncodriveclust.egg-info/entry_points.txt
oncodriveclust.egg-info/requires.txt
oncodriveclust.egg-info/top_level.txt