Metadata-Version: 1.1
Name: oncodriveclust
Version: 1.0.0
Summary: OncodriveCLUST
Home-page: https://bitbucket.org/bbglab/oncodriveclust
Author: Barcelona Biomedical Genomics research group
Author-email: nuria.lopez@upf.edu
License: UPF Free Source Code
Platform: UNKNOWN
Classifier: Development Status :: 4 - Beta
Classifier: Environment :: Console
Classifier: Intended Audience :: Science/Research
Classifier: Natural Language :: English
Classifier: Operating System :: OS Independent
Classifier: Programming Language :: Python
Classifier: Programming Language :: Python :: 2.7
Classifier: Topic :: Scientific/Engineering
Classifier: Topic :: Scientific/Engineering :: Bio-Informatics
